openactions/__init__.py
openactions-0.0.0.dist-info/METADATA
openactions-0.0.0.dist-info/WHEEL
openactions-0.0.0.dist-info/top_level.txt
openactions-0.0.0.dist-info/RECORD
