Metadata-Version: 2.1
Name: openactions
Version: 0.0.0
Summary: Coming soon
Author-email: openactions <contact@openactions.ai>
